_stabletrees.cp39-win_amd64.pyd
stabletrees/AGTBoost.py
stabletrees/PoissonTree.py
stabletrees/__init__.py
stabletrees/gradient_tree_boosting.py
stabletrees/random_forest.py
stabletrees/tree.py
stabletrees-0.1.1.dist-info/METADATA
stabletrees-0.1.1.dist-info/WHEEL
stabletrees-0.1.1.dist-info/top_level.txt
stabletrees-0.1.1.dist-info/RECORD
